textbased_textbased/__init__.py
textbased_textbased/main.py
textbased-0.0.1.dist-info/LICENSE
textbased-0.0.1.dist-info/METADATA
textbased-0.0.1.dist-info/WHEEL
textbased-0.0.1.dist-info/top_level.txt
textbased-0.0.1.dist-info/RECORD
